fv/__init__.py
fv/_base_client.py
fv/_client.py
fv/_compat.py
fv/_constants.py
fv/_exceptions.py
fv/_files.py
fv/_models.py
fv/_qs.py
fv/_resource.py
fv/_response.py
fv/_streaming.py
fv/_types.py
fv/_version.py
fv/py.typed
fv/_utils/__init__.py
fv/_utils/_logs.py
fv/_utils/_proxy.py
fv/_utils/_reflection.py
fv/_utils/_resources_proxy.py
fv/_utils/_streams.py
fv/_utils/_sync.py
fv/_utils/_transform.py
fv/_utils/_typing.py
fv/_utils/_utils.py
fv/lib/.keep
fv/resources/__init__.py
fv/resources/auth.py
fv/resources/card.py
fv/resources/match.py
fv/resources/pack.py
fv/resources/profit.py
fv/resources/redeem.py
fv/resources/userinventory.py
fv/resources/lineup/__init__.py
fv/resources/lineup/card.py
fv/resources/lineup/image.py
fv/resources/lineup/lineup.py
fv/resources/me/__init__.py
fv/resources/me/card.py
fv/resources/me/me.py
fv/resources/me/pack/__init__.py
fv/resources/me/pack/config.py
fv/resources/me/pack/pack.py
fv/resources/user/__init__.py
fv/resources/user/me.py
fv/resources/user/user.py
fv/types/__init__.py
fv/types/auth_login_discord_params.py
fv/types/auth_login_discord_response.py
fv/types/lineup_set_config_response.py
fv/types/match_join_ranked_response.py
fv/types/pack_list_response.py
fv/types/profit_calculate_response.py
fv/types/redeem_redeem_code_params.py
fv/types/redeem_redeem_code_response.py
fv/types/userinventory_redeem_response.py
fv/types/lineup/__init__.py
fv/types/lineup/card_up_params.py
fv/types/me/__init__.py
fv/types/me/card_hire_params.py
fv/types/me/card_hire_response.py
fv/types/me/card_sell_params.py
fv/types/me/card_sell_response.py
fv/types/me/card_update_params.py
fv/types/me/pack_buy_response.py
fv/types/me/pack_open_response.py
fv/types/me/pack/__init__.py
fv/types/me/pack/config_retrieve_response.py
fv/types/me/pack/config_update_params.py
fv/types/user/__init__.py
fv/types/user/me_update_language_params.py
fv/types/user/user.py
futverse-1.2.1.dist-info/METADATA
futverse-1.2.1.dist-info/WHEEL
futverse-1.2.1.dist-info/licenses/LICENSE
futverse-1.2.1.dist-info/RECORD
